Metadata-Version: 2.1
Name: pyVideoPreviewGenerator
Version: 1.0.2
Summary: Python based script to generate mini previews of your videos, like tutorials or ...
Home-page: https://github.com/soroushamdg/pyVideoPreviewGenerator
Author: @soroushamdg (soroushmpour)
Author-email: soroushmpour@gmail.com
License: UNKNOWN
Platform: UNKNOWN
Classifier: Programming Language :: Python :: 3
Classifier: License :: OSI Approved :: MIT License
Classifier: Operating System :: OS Independent
Requires-Python: >=3.6
